secretvaults/__init__.py
secretvaults/base.py
secretvaults/builder.py
secretvaults/logger.py
secretvaults/user.py
secretvaults/common/__init__.py
secretvaults/common/blindfold.py
secretvaults/common/cluster.py
secretvaults/common/keypair.py
secretvaults/common/nuc_cmd.py
secretvaults/common/paths.py
secretvaults/common/types.py
secretvaults/common/utils.py
secretvaults/dto/__init__.py
secretvaults/dto/builders.py
secretvaults/dto/collections.py
secretvaults/dto/common.py
secretvaults/dto/data.py
secretvaults/dto/queries.py
secretvaults/dto/system.py
secretvaults/dto/users.py
secretvaults/nildb/__init__.py
secretvaults/nildb/base_client.py
secretvaults/nildb/builder_client.py
secretvaults/nildb/user_client.py
secretvaults-0.3.2.dist-info/licenses/LICENSE
secretvaults-0.3.2.dist-info/METADATA
secretvaults-0.3.2.dist-info/WHEEL
secretvaults-0.3.2.dist-info/top_level.txt
secretvaults-0.3.2.dist-info/RECORD
