Metadata-Version: 2.4
Name: secretvaults
Version: 0.3.2
Summary: SDK for interacting with Nillion's Private Storage solutions.
License-Expression: MIT
Project-URL: Repository, https://github.com/NillionNetwork/secretvaults-py
Project-URL: Documentation, https://secretvaults.readthedocs.io
Requires-Python: >=3.12
License-File: LICENSE
Requires-Dist: aiohttp>=3.8.0
Requires-Dist: blindfold~=1.0.0rc0
Requires-Dist: nuc>=0.1.0
Requires-Dist: pydantic>=2.0.0
Requires-Dist: structlog>=23.0.0
Requires-Dist: python-dotenv>=1.1.1
Provides-Extra: docs
Requires-Dist: toml~=0.10.2; extra == "docs"
Requires-Dist: sphinx~=7.4; extra == "docs"
Requires-Dist: sphinx-rtd-theme~=3.0; extra == "docs"
Provides-Extra: test
Requires-Dist: pytest~=8.4; extra == "test"
Requires-Dist: pytest-cov~=7.0; extra == "test"
Requires-Dist: pytest-asyncio~=0.25.3; extra == "test"
Provides-Extra: lint
Requires-Dist: pylint~=3.3.0; extra == "lint"
Requires-Dist: black>=23.0.0; extra == "lint"
Provides-Extra: coveralls
Requires-Dist: coveralls~=4.0; extra == "coveralls"
Provides-Extra: publish
Requires-Dist: build~=0.10; extra == "publish"
Requires-Dist: twine~=4.0; extra == "publish"
Dynamic: license-file
